callm/__init__.py
callm/core/__init__.py
callm/core/engine.py
callm/core/io.py
callm/core/models.py
callm/core/rate_limit.py
callm/core/retry.py
callm/providers/__init__.py
callm/providers/anthropic.py
callm/providers/base.py
callm/providers/cohere.py
callm/providers/deepseek.py
callm/providers/gemini.py
callm/providers/models.py
callm/providers/openai.py
callm/providers/registry.py
callm/providers/voyageai.py
callm/tokenizers/__init__.py
callm/tokenizers/anthropic.py
callm/tokenizers/cohere.py
callm/tokenizers/deepseek.py
callm/tokenizers/gemini.py
callm/tokenizers/openai.py
callm/tokenizers/voyageai.py
callm/utils.py
callm_py-0.1.0.dist-info/WHEEL
callm_py-0.1.0.dist-info/entry_points.txt
callm_py-0.1.0.dist-info/METADATA
callm_py-0.1.0.dist-info/RECORD
