Metadata-Version: 2.3
Name: callm-py
Version: 0.1.0
Summary: Keep callm and process thousands of requests without (rate) limits.
Classifier: Development Status :: 3 - Alpha
Classifier: Intended Audience :: Developers
Classifier: Programming Language :: Python :: 3
Classifier: Programming Language :: Python :: 3.10
Classifier: Programming Language :: Python :: 3.11
Classifier: Programming Language :: Python :: 3.12
Classifier: Programming Language :: Python :: 3.13
Classifier: Programming Language :: Python :: 3.14
Requires-Dist: aiohttp>=3.12.15
Requires-Dist: loguru>=0.7.3
Requires-Dist: pydantic>=2.12.5
Requires-Dist: requests>=2.32.5
Requires-Dist: tiktoken>=0.11.0
Requires-Dist: tokenizers>=0.22.1
Requires-Dist: tqdm>=4.67.1
Requires-Python: >=3.10
